minimark/__init__.py
minimark/__main__.py
minimark/data/main.tcss
minimark/data/puppeteer-config.json
minimark/data/python_highlights.scm
minimark/data/treesitter-grammar_repos.txt
minimark-0.0.1.2.dist-info/LICENSE
minimark-0.0.1.2.dist-info/METADATA
minimark-0.0.1.2.dist-info/WHEEL
minimark-0.0.1.2.dist-info/entry_points.txt
minimark-0.0.1.2.dist-info/top_level.txt
minimark-0.0.1.2.dist-info/RECORD
