Metadata-Version: 2.1
Name: minimark
Version: 0.0.1.2
Summary: MiniMark : The CLI Markdown Editor / Viewer
Home-page: https://github.com/xbais/minimark
Author: Aakash Singh Bais
Author-email: xbais@duck.com
License: GPLv3
Classifier: Programming Language :: Python :: 3
Classifier: License :: OSI Approved :: GNU General Public License v3 (GPLv3)
Classifier: Operating System :: POSIX :: Linux
Requires-Python: >=3.6
License-File: LICENSE
Requires-Dist: numpy
Requires-Dist: argparse
Requires-Dist: textual
Requires-Dist: textual-image
Requires-Dist: matplotlib
Requires-Dist: pillow
Requires-Dist: cairosvg
Requires-Dist: tqdm
Requires-Dist: art
Requires-Dist: tree-sitter ==0.21.3
Requires-Dist: tree-sitter-languages ==1.10.2
Requires-Dist: asyncio
Requires-Dist: requests
